setup.py
tada0_toddler_neural_network.egg-info/PKG-INFO
tada0_toddler_neural_network.egg-info/SOURCES.txt
tada0_toddler_neural_network.egg-info/dependency_links.txt
tada0_toddler_neural_network.egg-info/top_level.txt
toddlernetwork/__init__.py
toddlernetwork/neural_network.py
toddlernetwork/nn_exceptions.py