Metadata-Version: 1.0
Name: tada0-toddler-neural-network
Version: 1.0.9
Summary: Little neural network library
Home-page: UNKNOWN
Author: Tomasz Hołda
Author-email: UNKNOWN
License: UNKNOWN
Platform: UNKNOWN
